LICENSE
MANIFEST.in
setup.py
codev_dashboard/__init__.py
codev_dashboard/__main__.py
codev_dashboard.egg-info/PKG-INFO
codev_dashboard.egg-info/SOURCES.txt
codev_dashboard.egg-info/dependency_links.txt
codev_dashboard.egg-info/requires.txt
codev_dashboard.egg-info/top_level.txt
codev_dashboard/static/css/bootstrap-theme.min.css
codev_dashboard/static/css/bootstrap.min.css
codev_dashboard/static/fonts/glyphicons-halflings-regular.eot
codev_dashboard/static/fonts/glyphicons-halflings-regular.svg
codev_dashboard/static/fonts/glyphicons-halflings-regular.ttf
codev_dashboard/static/fonts/glyphicons-halflings-regular.woff
codev_dashboard/static/fonts/glyphicons-halflings-regular.woff2
codev_dashboard/static/images/favicon.png
codev_dashboard/static/images/favicon.svg
codev_dashboard/static/js/bootstrap.min.js
codev_dashboard/static/js/npm.js
codev_dashboard/templates/index.html