Metadata-Version: 1.1
Name: codev-dashboard
Version: 0.1.2a1
Summary: codev dashboard
Home-page: UNKNOWN
Author: Jan Češpivo
Author-email: jan.cespivo@gmail.com
License: Apache 2.0
Platform: UNKNOWN
Classifier: Development Status :: 3 - Alpha
Classifier: Environment :: Web Environment
Classifier: Intended Audience :: Developers
Classifier: License :: OSI Approved :: Apache Software License
Classifier: Operating System :: OS Independent
Classifier: Programming Language :: Python
Classifier: Topic :: Internet :: WWW/HTTP
